pygpio/FT232H.py
pygpio/GPIO.py
pygpio/I2C.py
pygpio/MCP230xx.py
pygpio/PCF8574.py
pygpio/PWM.py
pygpio/Platform.py
pygpio/SPI.py
pygpio/__init__.py
pygpio-1.0.3.dist-info/DESCRIPTION.rst
pygpio-1.0.3.dist-info/METADATA
pygpio-1.0.3.dist-info/RECORD
pygpio-1.0.3.dist-info/WHEEL
pygpio-1.0.3.dist-info/metadata.json
pygpio-1.0.3.dist-info/top_level.txt
tests/MockGPIO.py
tests/__init__.py
tests/test_GPIO.py
tests/test_I2C.py
tests/test_PWM.py
tests/test_Platform.py
tests/test_SPI.py
