Metadata-Version: 2.0
Name: pygpio
Version: 1.0.3
Summary: UNKNOWN
Home-page: https://github.com/adafruit/Adafruit_Python_GPIO/
Author: Leonardo Lazzaro
Author-email: lazzaroleonardo@gmail.com
License: MIT
Platform: UNKNOWN
Requires-Dist: adafruit-pureio
